ares/__init__.py
ares/async_utils.py
ares/config.py
ares/config_test.py
ares/presets.py
ares/registry.py
ares/registry_test.py
ares/code_agents/__init__.py
ares/code_agents/code_agent_base.py
ares/code_agents/mini_swe_agent.py
ares/code_agents/terminus2/__init__.py
ares/code_agents/terminus2/json_parser.py
ares/code_agents/terminus2/json_parser_test.py
ares/code_agents/terminus2/terminus2_agent.py
ares/code_agents/terminus2/terminus2_agent_test.py
ares/code_agents/terminus2/xml_parser.py
ares/code_agents/terminus2/xml_parser_test.py
ares/code_agents/terminus2/templates/summarize.txt
ares/code_agents/terminus2/templates/terminus-json-plain.txt
ares/code_agents/terminus2/templates/terminus-xml-plain.txt
ares/code_agents/terminus2/templates/timeout.txt
ares/containers/__init__.py
ares/containers/containers.py
ares/containers/daytona.py
ares/containers/docker.py
ares/contrib/README.md
ares/contrib/__init__.py
ares/contrib/eval_visualizer.py
ares/contrib/llama_cpp.py
ares/environments/__init__.py
ares/environments/base.py
ares/environments/code_env.py
ares/environments/utils.py
ares/experiment_tracking/__init__.py
ares/experiment_tracking/stat_tracker.py
ares/experiment_tracking/tensorboard.py
ares/llms/__init__.py
ares/llms/accounting.py
ares/llms/chat_completions_compatible.py
ares/llms/llm_clients.py
ares/llms/queue_mediated_client.py
ares/llms/request.py
ares/llms/request_test.py
ares/llms/response.py
ares/testing/__init__.py
ares/testing/mock_container.py
ares/testing/mock_container_test.py
ares/testing/mock_llm.py
ares/testing/mock_llm_test.py
martian_ares-0.0.2.dist-info/METADATA
martian_ares-0.0.2.dist-info/WHEEL
martian_ares-0.0.2.dist-info/licenses/LICENSE
martian_ares-0.0.2.dist-info/RECORD
