Metadata-Version: 2.4
Name: martian-ares
Version: 0.0.2
Summary: Agentic Research and Evaluation Suite
Project-URL: Homepage, https://github.com/withmartian/ares
Project-URL: Repository, https://github.com/withmartian/ares
Author-email: Joshua Greaves <josh@withmartian.com>, Ryan Smith <ryan@withmartian.com>, Alex Zverianskii <alex@withmartian.com>
License: MIT License
License-File: LICENSE
Requires-Python: >=3.12
Requires-Dist: anthropic>=0.76.0
Requires-Dist: daytona>=0.125.0
Requires-Dist: docker>=7.1.0
Requires-Dist: frozendict>=2.4.7
Requires-Dist: harbor>=0.1.32
Requires-Dist: httpx>=0.28.1
Requires-Dist: jinja2>=3.1.6
Requires-Dist: mini-swe-agent>=1.17.3
Requires-Dist: numpy>=2.3.5
Requires-Dist: openai<=1.100.0
Requires-Dist: pydantic-settings>=2.12.0
Requires-Dist: pydantic>=2.12.5
Requires-Dist: pyyaml>=6.0.3
Requires-Dist: swebench>=4.1.0
Requires-Dist: tenacity>=9.1.2
Provides-Extra: docs
Requires-Dist: sphinx-autodoc-typehints>=1.25.0; extra == 'docs'
Requires-Dist: sphinx-rtd-theme>=2.0.0; extra == 'docs'
Requires-Dist: sphinx>=7.0.0; extra == 'docs'
Provides-Extra: eval-viz
Requires-Dist: rich>=13.7.0; extra == 'eval-viz'
Requires-Dist: textual>=1.0.0; extra == 'eval-viz'
Provides-Extra: llamacpp
Requires-Dist: llama-cpp-python>=0.3.16; extra == 'llamacpp'
Provides-Extra: tensorboard
Requires-Dist: tensorboard>=2.20.0; extra == 'tensorboard'
Requires-Dist: torch>=2.9.1; extra == 'tensorboard'
